tools/__init__.py
tools/regenerate_mypy_ignores.py
zigpy/__init__.py
zigpy/appdb.py
zigpy/application.py
zigpy/backups.py
zigpy/const.py
zigpy/datastructures.py
zigpy/device.py
zigpy/endpoint.py
zigpy/exceptions.py
zigpy/group.py
zigpy/listeners.py
zigpy/py.typed
zigpy/serial.py
zigpy/state.py
zigpy/topology.py
zigpy/typing.py
zigpy/util.py
zigpy/appdb_schemas/__init__.py
zigpy/appdb_schemas/schema_v0.sql
zigpy/appdb_schemas/schema_v1.sql
zigpy/appdb_schemas/schema_v10.sql
zigpy/appdb_schemas/schema_v11.sql
zigpy/appdb_schemas/schema_v12.sql
zigpy/appdb_schemas/schema_v13.sql
zigpy/appdb_schemas/schema_v14.sql
zigpy/appdb_schemas/schema_v2.sql
zigpy/appdb_schemas/schema_v3.sql
zigpy/appdb_schemas/schema_v4.sql
zigpy/appdb_schemas/schema_v5.sql
zigpy/appdb_schemas/schema_v6.sql
zigpy/appdb_schemas/schema_v7.sql
zigpy/appdb_schemas/schema_v8.sql
zigpy/appdb_schemas/schema_v9.sql
zigpy/backports/__init__.py
zigpy/config/__init__.py
zigpy/config/defaults.py
zigpy/config/validators.py
zigpy/event/__init__.py
zigpy/event/event_base.py
zigpy/ota/__init__.py
zigpy/ota/image.py
zigpy/ota/json_schemas.py
zigpy/ota/manager.py
zigpy/ota/providers.py
zigpy/ota/validators.py
zigpy/profiles/__init__.py
zigpy/profiles/zgp.py
zigpy/profiles/zha.py
zigpy/profiles/zll.py
zigpy/quirks/__init__.py
zigpy/quirks/registry.py
zigpy/quirks/v2/__init__.py
zigpy/quirks/v2/homeassistant/__init__.py
zigpy/quirks/v2/homeassistant/binary_sensor.py
zigpy/quirks/v2/homeassistant/number.py
zigpy/quirks/v2/homeassistant/sensor.py
zigpy/types/__init__.py
zigpy/types/basic.py
zigpy/types/named.py
zigpy/types/struct.py
zigpy/zcl/__init__.py
zigpy/zcl/foundation.py
zigpy/zcl/helpers.py
zigpy/zcl/clusters/__init__.py
zigpy/zcl/clusters/closures.py
zigpy/zcl/clusters/general.py
zigpy/zcl/clusters/general_const.py
zigpy/zcl/clusters/greenpower.py
zigpy/zcl/clusters/homeautomation.py
zigpy/zcl/clusters/hvac.py
zigpy/zcl/clusters/lighting.py
zigpy/zcl/clusters/lightlink.py
zigpy-0.91.5.dist-info/licenses/COPYING
zigpy-0.91.5.dist-info/licenses/LICENSE
zigpy-0.91.5.dist-info/METADATA
zigpy-0.91.5.dist-info/WHEEL
zigpy-0.91.5.dist-info/top_level.txt
zigpy-0.91.5.dist-info/RECORD
