Metadata-Version: 2.4
Name: zigpy
Version: 0.91.5
Summary: Library implementing a Zigbee stack
Author-email: Russell Cloran <rcloran@gmail.com>
License: GPL-3.0
Project-URL: repository, https://github.com/zigpy/zigpy
Requires-Python: >=3.11
License-File: LICENSE
License-File: COPYING
Requires-Dist: attrs
Requires-Dist: aiohttp
Requires-Dist: aiosqlite<0.22.0,>=0.20.0
Requires-Dist: crccheck
Requires-Dist: cryptography
Requires-Dist: voluptuous
Requires-Dist: jsonschema
Requires-Dist: pyserial-asyncio-fast
Requires-Dist: typing_extensions
Requires-Dist: frozendict
Dynamic: license-file
